pyNacha/__init__.py
pyNacha/builder.py
pyNacha/data_types.py
pyNacha/parser.py
pyNacha-0.0.3.dist-info/LICENSE
pyNacha-0.0.3.dist-info/METADATA
pyNacha-0.0.3.dist-info/WHEEL
pyNacha-0.0.3.dist-info/top_level.txt
pyNacha-0.0.3.dist-info/RECORD
