Metadata-Version: 2.1
Name: pyNacha
Version: 0.0.3
Summary: ACH NACHA CCD+ file generator module for python.
Home-page: https://github.com/asinha10/pyNacha.git
Author: Aakash Sinha
Author-email: aakashtheaks@gmail.com
License: UNKNOWN
Project-URL: Bug Tracker, https://github.com/pypa/sampleproject/issues
Platform: UNKNOWN
Classifier: Programming Language :: Python :: 3
Classifier: License :: OSI Approved :: MIT License
Classifier: Operating System :: OS Independent
Requires-Python: >=3.6
License-File: LICENSE
